jslog4kube/__init__.py
jslog4kube/bootstrap.py
jslog4kube/gunicorn/__init__.py
jslog4kube/gunicorn/dictconfig_logger.py
jslog4kube/kube/__init__.py
jslog4kube/kube/log_config.py
jslog4kube/kube/metadata_injector.py
jslog4kube-1.0.7.dist-info/licenses/AUTHORS.txt
jslog4kube-1.0.7.dist-info/licenses/LICENSE
jslog4kube-1.0.7.dist-info/METADATA
jslog4kube-1.0.7.dist-info/WHEEL
jslog4kube-1.0.7.dist-info/top_level.txt
jslog4kube-1.0.7.dist-info/RECORD
