Metadata-Version: 2.4
Name: jslog4kube
Version: 1.0.7
Summary: relatively hassle-free JSON logging for Kubernetes pods
Author-email: Frank Wiles <frank@revsys.com>, "Stephen D. Spencer" <stephen@revsys.com>
License-Expression: MIT
Project-URL: Homepage, https://github.com/revsys/jslog4kube
Classifier: Development Status :: 5 - Production/Stable
Classifier: Intended Audience :: Developers
Classifier: Programming Language :: Python :: 3
Classifier: Programming Language :: Python :: 3.9
Classifier: Programming Language :: Python :: 3.10
Classifier: Programming Language :: Python :: 3.11
Classifier: Programming Language :: Python :: 3.12
Classifier: Programming Language :: Python :: 3.13
Requires-Python: >=3.9
License-File: LICENSE
License-File: AUTHORS.txt
Requires-Dist: python-json-logger
Provides-Extra: dev
Requires-Dist: bumpversion; extra == "dev"
Requires-Dist: uv; extra == "dev"
Dynamic: license-file
